rpnparse/__init__.py
rpnparse/rpnparse.py
rpnparse-0.0.1.dist-info/DESCRIPTION.rst
rpnparse-0.0.1.dist-info/METADATA
rpnparse-0.0.1.dist-info/RECORD
rpnparse-0.0.1.dist-info/WHEEL
rpnparse-0.0.1.dist-info/entry_points.txt
rpnparse-0.0.1.dist-info/metadata.json
rpnparse-0.0.1.dist-info/top_level.txt
