Metadata-Version: 2.0
Name: rpnparse
Version: 0.0.1
Summary: simple reverse polish notation parser to learn how to write parsers
Home-page: https://github.com/smartsammler/rpnparse
Author: Julian Gethmann
Author-email: smartsammler@gmail.com
License: new-bsd
Platform: UNKNOWN
Classifier: Development Status :: 4 - Beta
Classifier: Programming Language :: Python
Classifier: Intended Audience :: Science/Research
Classifier: Topic :: Scientific/Engineering
Classifier: Topic :: System :: Shells
Classifier: Topic :: Software Development :: Interpreters
